llama_index/packs/docugami_kg_rag/__init__.py
llama_index/packs/docugami_kg_rag/base.py
llama_index/packs/docugami_kg_rag/config/__init__.py
llama_index/packs/docugami_kg_rag/helpers/__init__.py
llama_index/packs/docugami_kg_rag/helpers/fused_summary_retriever.py
llama_index/packs/docugami_kg_rag/helpers/indexing.py
llama_index/packs/docugami_kg_rag/helpers/prompts.py
llama_index/packs/docugami_kg_rag/helpers/reports.py
llama_index/packs/docugami_kg_rag/helpers/retrieval.py
llama_index/packs/docugami_kg_rag/helpers/summaries.py
llama_index/packs/docugami_kg_rag/helpers/vector_store.py
llama_index_packs_docugami_kg_rag-0.3.0.dist-info/METADATA
llama_index_packs_docugami_kg_rag-0.3.0.dist-info/WHEEL
llama_index_packs_docugami_kg_rag-0.3.0.dist-info/RECORD
