Metadata-Version: 2.1
Name: llama-index-packs-docugami-kg-rag
Version: 0.3.0
Summary: This template contains a reference architecture for Retrieval Augmented Generation against a set of documents using Docugami's XML Knowledge Graph (KG-RAG).
Keywords: infer,rag,retrieve,retriever
Author: Docugami
Author-email: contact@docugami.com
Requires-Python: >=3.9,<4.0
Classifier: Programming Language :: Python :: 3
Classifier: Programming Language :: Python :: 3.9
Classifier: Programming Language :: Python :: 3.10
Classifier: Programming Language :: Python :: 3.11
Classifier: Programming Language :: Python :: 3.12
Requires-Dist: dgml-utils (>=0.3.2,<0.4.0)
Requires-Dist: docugami (>=0.1.2,<0.2.0)
Requires-Dist: llama-index-embeddings-openai (>=0.3.0,<0.4.0)
Requires-Dist: llama-index-llms-openai (>=0.3.0,<0.4.0)
Requires-Dist: llama-index-readers-docugami (>=0.3.0,<0.4.0)
Requires-Dist: llama-index-vector-stores-chroma (>=0.4.0,<0.5.0)
Requires-Dist: lxml (==4.9.3)
Requires-Dist: openpyxl (>=3.1.2,<4.0.0)
Requires-Dist: pandas
